{
  "bicycle": {
    "confidence": [
      NaN,
      NaN,
      NaN,
      NaN,
      NaN,
      NaN,
      NaN,
      NaN,
      NaN,
      NaN,
      NaN,
      NaN,
      NaN,
      NaN,
      NaN,
      NaN,
      NaN,
      NaN,
      NaN,
      NaN,
      NaN,
      -0.13983726833333335,
      -0.13983726833333335,
      -0.13983726833333335,
      -0.06726780212079436,
      0.4497896446862932,
      0.4497896446862932,
      0.4497896446862932,
      0.4497896446862932,
      0.4497896446862932,
      0.4497896446862932,
      0.47404385601149135,
      0.49905601143836975,
      0.49905601143836975,
      0.5362354076809319,
      0.7241471660812159,
      0.7517578952714539,
      0.7517578952714539,
      0.7976642038974406,
      0.8050420034983216
    ],
    "recall_hypo": [
      1.0,
      0.976923076923,
      0.953846153846,
      0.930769230769,
      0.907692307692,
      0.884615384615,
      0.861538461538,
      0.838461538462,
      0.815384615385,
      0.792307692308,
      0.769230769231,
      0.746153846154,
      0.723076923077,
      0.7,
      0.676923076923,
      0.653846153846,
      0.630769230769,
      0.607692307692,
      0.584615384615,
      0.561538461538,
      0.538461538462,
      0.515384615385,
      0.492307692308,
      0.469230769231,
      0.446153846154,
      0.423076923077,
      0.4,
      0.376923076923,
      0.353846153846,
      0.330769230769,
      0.307692307692,
      0.284615384615,
      0.261538461538,
      0.238461538462,
      0.215384615385,
      0.192307692308,
      0.169230769231,
      0.146153846154,
      0.123076923077,
      0.1
    ],
    "lgd": [
      NaN,
      NaN,
      NaN,
      NaN,
      NaN,
      NaN,
      NaN,
      NaN,
      NaN,
      NaN,
      NaN,
      NaN,
      NaN,
      NaN,
      NaN,
      NaN,
      NaN,
      NaN,
      NaN,
      NaN,
      NaN,
      1.0,
      1.0,
      1.0,
      1.5,
      1.5,
      1.5,
      1.5,
      1.5,
      1.5,
      1.5,
      2.0,
      2.0,
      2.0,
      1.5,
      1.8333333333333333,
      1.8333333333333333,
      1.8333333333333333,
      1.25,
      1.25
    ],
    "frag": [
      NaN,
      NaN,
      NaN,
      NaN,
      NaN,
      NaN,
      NaN,
      NaN,
      NaN,
      NaN,
      NaN,
      NaN,
      NaN,
      NaN,
      NaN,
      NaN,
      NaN,
      NaN,
      NaN,
      NaN,
      NaN,
      3.0,
      3.0,
      3.0,
      3.0,
      3.0,
      3.0,
      3.0,
      3.0,
      3.0,
      3.0,
      1.0,
      1.0,
      1.0,
      0.0,
      0.0,
      0.0,
      0.0,
      0.0,
      0.0
    ],
    "recall": [
      NaN,
      NaN,
      NaN,
      NaN,
      NaN,
      NaN,
      NaN,
      NaN,
      NaN,
      NaN,
      NaN,
      NaN,
      NaN,
      NaN,
      NaN,
      NaN,
      NaN,
      NaN,
      NaN,
      NaN,
      NaN,
      0.5862068965517241,
      0.5862068965517241,
      0.5862068965517241,
      0.4827586206896552,
      0.4827586206896552,
      0.4827586206896552,
      0.4827586206896552,
      0.4827586206896552,
      0.4827586206896552,
      0.4827586206896552,
      0.3275862068965517,
      0.3275862068965517,
      0.3275862068965517,
      0.22413793103448276,
      0.20689655172413793,
      0.20689655172413793,
      0.20689655172413793,
      0.1206896551724138,
      0.1206896551724138
    ],
    "tid": [
      NaN,
      NaN,
      NaN,
      NaN,
      NaN,
      NaN,
      NaN,
      NaN,
      NaN,
      NaN,
      NaN,
      NaN,
      NaN,
      NaN,
      NaN,
      NaN,
      NaN,
      NaN,
      NaN,
      NaN,
      NaN,
      0.4166666666666667,
      0.4166666666666667,
      0.4166666666666667,
      0.9166666666666666,
      0.9166666666666666,
      0.9166666666666666,
      0.9166666666666666,
      0.9166666666666666,
      0.9166666666666666,
      0.9166666666666666,
      1.6666666666666667,
      1.6666666666666667,
      1.6666666666666667,
      1.0,
      1.1666666666666667,
      1.1666666666666667,
      1.1666666666666667,
      0.25,
      0.25
    ],
    "fn": [
      NaN,
      NaN,
      NaN,
      NaN,
      NaN,
      NaN,
      NaN,
      NaN,
      NaN,
      NaN,
      NaN,
      NaN,
      NaN,
      NaN,
      NaN,
      NaN,
      NaN,
      NaN,
      NaN,
      NaN,
      NaN,
      24.0,
      24.0,
      24.0,
      30.0,
      30.0,
      30.0,
      30.0,
      30.0,
      30.0,
      30.0,
      39.0,
      39.0,
      39.0,
      45.0,
      46.0,
      46.0,
      46.0,
      51.0,
      51.0
    ],
    "fp": [
      NaN,
      NaN,
      NaN,
      NaN,
      NaN,
      NaN,
      NaN,
      NaN,
      NaN,
      NaN,
      NaN,
      NaN,
      NaN,
      NaN,
      NaN,
      NaN,
      NaN,
      NaN,
      NaN,
      NaN,
      NaN,
      22.0,
      22.0,
      22.0,
      22.0,
      20.0,
      20.0,
      20.0,
      20.0,
      20.0,
      20.0,
      17.0,
      17.0,
      17.0,
      15.0,
      2.0,
      2.0,
      2.0,
      1.0,
      1.0
    ],
    "tp": [
      NaN,
      NaN,
      NaN,
      NaN,
      NaN,
      NaN,
      NaN,
      NaN,
      NaN,
      NaN,
      NaN,
      NaN,
      NaN,
      NaN,
      NaN,
      NaN,
      NaN,
      NaN,
      NaN,
      NaN,
      NaN,
      31.0,
      31.0,
      31.0,
      26.0,
      26.0,
      26.0,
      26.0,
      26.0,
      26.0,
      26.0,
      19.0,
      19.0,
      19.0,
      13.0,
      12.0,
      12.0,
      12.0,
      7.0,
      7.0
    ],
    "ids": [
      NaN,
      NaN,
      NaN,
      NaN,
      NaN,
      NaN,
      NaN,
      NaN,
      NaN,
      NaN,
      NaN,
      NaN,
      NaN,
      NaN,
      NaN,
      NaN,
      NaN,
      NaN,
      NaN,
      NaN,
      NaN,
      3.0,
      3.0,
      3.0,
      2.0,
      2.0,
      2.0,
      2.0,
      2.0,
      2.0,
      2.0,
      0.0,
      0.0,
      0.0,
      0.0,
      0.0,
      0.0,
      0.0,
      0.0,
      0.0
    ],
    "motar": [
      NaN,
      NaN,
      NaN,
      NaN,
      NaN,
      NaN,
      NaN,
      NaN,
      NaN,
      NaN,
      NaN,
      NaN,
      NaN,
      NaN,
      NaN,
      NaN,
      NaN,
      NaN,
      NaN,
      NaN,
      NaN,
      0.29032258064516137,
      0.29032258064516137,
      0.29032258064516137,
      0.15384615384615385,
      0.23076923076923073,
      0.23076923076923073,
      0.23076923076923073,
      0.23076923076923073,
      0.23076923076923073,
      0.23076923076923073,
      0.10526315789473684,
      0.10526315789473684,
      0.10526315789473684,
      0.0,
      0.8333333333333334,
      0.8333333333333334,
      0.8333333333333334,
      0.8571428571428572,
      0.8571428571428572
    ],
    "mt": [
      NaN,
      NaN,
      NaN,
      NaN,
      NaN,
      NaN,
      NaN,
      NaN,
      NaN,
      NaN,
      NaN,
      NaN,
      NaN,
      NaN,
      NaN,
      NaN,
      NaN,
      NaN,
      NaN,
      NaN,
      NaN,
      1.0,
      1.0,
      1.0,
      0.0,
      0.0,
      0.0,
      0.0,
      0.0,
      0.0,
      0.0,
      0.0,
      0.0,
      0.0,
      0.0,
      0.0,
      0.0,
      0.0,
      0.0,
      0.0
    ],
    "faf": [
      NaN,
      NaN,
      NaN,
      NaN,
      NaN,
      NaN,
      NaN,
      NaN,
      NaN,
      NaN,
      NaN,
      NaN,
      NaN,
      NaN,
      NaN,
      NaN,
      NaN,
      NaN,
      NaN,
      NaN,
      NaN,
      51.162790697674424,
      51.162790697674424,
      51.162790697674424,
      51.162790697674424,
      46.51162790697674,
      46.51162790697674,
      46.51162790697674,
      46.51162790697674,
      46.51162790697674,
      46.51162790697674,
      39.53488372093023,
      39.53488372093023,
      39.53488372093023,
      34.883720930232556,
      5.128205128205128,
      5.128205128205128,
      5.128205128205128,
      2.564102564102564,
      2.564102564102564
    ],
    "ml": [
      NaN,
      NaN,
      NaN,
      NaN,
      NaN,
      NaN,
      NaN,
      NaN,
      NaN,
      NaN,
      NaN,
      NaN,
      NaN,
      NaN,
      NaN,
      NaN,
      NaN,
      NaN,
      NaN,
      NaN,
      NaN,
      2.0,
      2.0,
      2.0,
      2.0,
      2.0,
      2.0,
      2.0,
      2.0,
      2.0,
      2.0,
      3.0,
      3.0,
      3.0,
      4.0,
      5.0,
      5.0,
      5.0,
      6.0,
      6.0
    ],
    "gt": [
      NaN,
      NaN,
      NaN,
      NaN,
      NaN,
      NaN,
      NaN,
      NaN,
      NaN,
      NaN,
      NaN,
      NaN,
      NaN,
      NaN,
      NaN,
      NaN,
      NaN,
      NaN,
      NaN,
      NaN,
      NaN,
      58.0,
      58.0,
      58.0,
      58.0,
      58.0,
      58.0,
      58.0,
      58.0,
      58.0,
      58.0,
      58.0,
      58.0,
      58.0,
      58.0,
      58.0,
      58.0,
      58.0,
      58.0,
      58.0
    ],
    "mota": [
      NaN,
      NaN,
      NaN,
      NaN,
      NaN,
      NaN,
      NaN,
      NaN,
      NaN,
      NaN,
      NaN,
      NaN,
      NaN,
      NaN,
      NaN,
      NaN,
      NaN,
      NaN,
      NaN,
      NaN,
      NaN,
      0.15517241379310343,
      0.15517241379310343,
      0.15517241379310343,
      0.06896551724137934,
      0.10344827586206895,
      0.10344827586206895,
      0.10344827586206895,
      0.10344827586206895,
      0.10344827586206895,
      0.10344827586206895,
      0.03448275862068961,
      0.03448275862068961,
      0.03448275862068961,
      0.0,
      0.1724137931034483,
      0.1724137931034483,
      0.1724137931034483,
      0.10344827586206895,
      0.10344827586206895
    ],
    "motp": [
      NaN,
      NaN,
      NaN,
      NaN,
      NaN,
      NaN,
      NaN,
      NaN,
      NaN,
      NaN,
      NaN,
      NaN,
      NaN,
      NaN,
      NaN,
      NaN,
      NaN,
      NaN,
      NaN,
      NaN,
      NaN,
      0.6710912029500887,
      0.6710912029500887,
      0.6710912029500887,
      0.6965769815574282,
      0.6965769814921666,
      0.6965769814921666,
      0.6965769814921666,
      0.6965769814921666,
      0.6965769814921666,
      0.6965769814921666,
      0.8129525665882174,
      0.8129525665882174,
      0.8129525665882174,
      0.69909234177,
      0.7275533309427065,
      0.7275533309427065,
      0.7275533309427065,
      0.549423585716033,
      0.549423585716033
    ]
  },
  "bus": {
    "confidence": [
      NaN,
      NaN,
      NaN,
      NaN,
      NaN,
      NaN,
      NaN,
      NaN,
      NaN,
      NaN,
      NaN,
      NaN,
      NaN,
      NaN,
      NaN,
      NaN,
      NaN,
      NaN,
      0.5414398787620545,
      0.5414398787620545,
      0.5668556094169617,
      0.722588597686666,
      0.722588597686666,
      0.722588597686666,
      0.722588597686666,
      0.722588597686666,
      0.722588597686666,
      0.722588597686666,
      0.722588597686666,
      0.722588597686666,
      0.722588597686666,
      0.722588597686666,
      0.722588597686666,
      0.722588597686666,
      0.722588597686666,
      0.722588597686666,
      0.727612910909091,
      0.727612910909091,
      0.727612910909091,
      0.727612910909091
    ],
    "recall_hypo": [
      1.0,
      0.976923076923,
      0.953846153846,
      0.930769230769,
      0.907692307692,
      0.884615384615,
      0.861538461538,
      0.838461538462,
      0.815384615385,
      0.792307692308,
      0.769230769231,
      0.746153846154,
      0.723076923077,
      0.7,
      0.676923076923,
      0.653846153846,
      0.630769230769,
      0.607692307692,
      0.584615384615,
      0.561538461538,
      0.538461538462,
      0.515384615385,
      0.492307692308,
      0.469230769231,
      0.446153846154,
      0.423076923077,
      0.4,
      0.376923076923,
      0.353846153846,
      0.330769230769,
      0.307692307692,
      0.284615384615,
      0.261538461538,
      0.238461538462,
      0.215384615385,
      0.192307692308,
      0.169230769231,
      0.146153846154,
      0.123076923077,
      0.1
    ],
    "lgd": [
      NaN,
      NaN,
      NaN,
      NaN,
      NaN,
      NaN,
      NaN,
      NaN,
      NaN,
      NaN,
      NaN,
      NaN,
      NaN,
      NaN,
      NaN,
      NaN,
      NaN,
      NaN,
      2.5,
      2.5,
      2.75,
      3.6666666666666665,
      3.6666666666666665,
      3.6666666666666665,
      3.6666666666666665,
      3.6666666666666665,
      3.6666666666666665,
      3.6666666666666665,
      3.6666666666666665,
      3.6666666666666665,
      3.6666666666666665,
      3.6666666666666665,
      3.6666666666666665,
      3.6666666666666665,
      3.6666666666666665,
      3.6666666666666665,
      4.75,
      4.75,
      4.75,
      4.75
    ],
    "frag": [
      NaN,
      NaN,
      NaN,
      NaN,
      NaN,
      NaN,
      NaN,
      NaN,
      NaN,
      NaN,
      NaN,
      NaN,
      NaN,
      NaN,
      NaN,
      NaN,
      NaN,
      NaN,
      1.0,
      1.0,
      1.0,
      1.0,
      1.0,
      1.0,
      1.0,
      1.0,
      1.0,
      1.0,
      1.0,
      1.0,
      1.0,
      1.0,
      1.0,
      1.0,
      1.0,
      1.0,
      1.0,
      1.0,
      1.0,
      1.0
    ],
    "recall": [
      NaN,
      NaN,
      NaN,
      NaN,
      NaN,
      NaN,
      NaN,
      NaN,
      NaN,
      NaN,
      NaN,
      NaN,
      NaN,
      NaN,
      NaN,
      NaN,
      NaN,
      NaN,
      0.5930232558139535,
      0.5930232558139535,
      0.5465116279069767,
      0.5232558139534884,
      0.5232558139534884,
      0.5232558139534884,
      0.5232558139534884,
      0.5232558139534884,
      0.5232558139534884,
      0.5232558139534884,
      0.5232558139534884,
      0.5232558139534884,
      0.5232558139534884,
      0.5232558139534884,
      0.5232558139534884,
      0.5232558139534884,
      0.5232558139534884,
      0.5232558139534884,
      0.1744186046511628,
      0.1744186046511628,
      0.1744186046511628,
      0.1744186046511628
    ],
    "tid": [
      NaN,
      NaN,
      NaN,
      NaN,
      NaN,
      NaN,
      NaN,
      NaN,
      NaN,
      NaN,
      NaN,
      NaN,
      NaN,
      NaN,
      NaN,
      NaN,
      NaN,
      NaN,
      1.6,
      1.6,
      2.0,
      2.6666666666666665,
      2.6666666666666665,
      2.6666666666666665,
      2.6666666666666665,
      2.6666666666666665,
      2.6666666666666665,
      2.6666666666666665,
      2.6666666666666665,
      2.6666666666666665,
      2.6666666666666665,
      2.6666666666666665,
      2.6666666666666665,
      2.6666666666666665,
      2.6666666666666665,
      2.6666666666666665,
      4.0,
      4.0,
      4.0,
      4.0
    ],
    "fn": [
      NaN,
      NaN,
      NaN,
      NaN,
      NaN,
      NaN,
      NaN,
      NaN,
      NaN,
      NaN,
      NaN,
      NaN,
      NaN,
      NaN,
      NaN,
      NaN,
      NaN,
      NaN,
      35.0,
      35.0,
      39.0,
      41.0,
      41.0,
      41.0,
      41.0,
      41.0,
      41.0,
      41.0,
      41.0,
      41.0,
      41.0,
      41.0,
      41.0,
      41.0,
      41.0,
      41.0,
      71.0,
      71.0,
      71.0,
      71.0
    ],
    "fp": [
      NaN,
      NaN,
      NaN,
      NaN,
      NaN,
      NaN,
      NaN,
      NaN,
      NaN,
      NaN,
      NaN,
      NaN,
      NaN,
      NaN,
      NaN,
      NaN,
      NaN,
      NaN,
      1.0,
      1.0,
      1.0,
      1.0,
      1.0,
      1.0,
      1.0,
      1.0,
      1.0,
      1.0,
      1.0,
      1.0,
      1.0,
      1.0,
      1.0,
      1.0,
      1.0,
      1.0,
      1.0,
      1.0,
      1.0,
      1.0
    ],
    "tp": [
      NaN,
      NaN,
      NaN,
      NaN,
      NaN,
      NaN,
      NaN,
      NaN,
      NaN,
      NaN,
      NaN,
      NaN,
      NaN,
      NaN,
      NaN,
      NaN,
      NaN,
      NaN,
      51.0,
      51.0,
      47.0,
      45.0,
      45.0,
      45.0,
      45.0,
      45.0,
      45.0,
      45.0,
      45.0,
      45.0,
      45.0,
      45.0,
      45.0,
      45.0,
      45.0,
      45.0,
      15.0,
      15.0,
      15.0,
      15.0
    ],
    "ids": [
      NaN,
      NaN,
      NaN,
      NaN,
      NaN,
      NaN,
      NaN,
      NaN,
      NaN,
      NaN,
      NaN,
      NaN,
      NaN,
      NaN,
      NaN,
      NaN,
      NaN,
      NaN,
      0.0,
      0.0,
      0.0,
      0.0,
      0.0,
      0.0,
      0.0,
      0.0,
      0.0,
      0.0,
      0.0,
      0.0,
      0.0,
      0.0,
      0.0,
      0.0,
      0.0,
      0.0,
      0.0,
      0.0,
      0.0,
      0.0
    ],
    "motar": [
      NaN,
      NaN,
      NaN,
      NaN,
      NaN,
      NaN,
      NaN,
      NaN,
      NaN,
      NaN,
      NaN,
      NaN,
      NaN,
      NaN,
      NaN,
      NaN,
      NaN,
      NaN,
      0.980392156862745,
      0.980392156862745,
      0.9787234042553191,
      0.9777777777777777,
      0.9777777777777777,
      0.9777777777777777,
      0.9777777777777777,
      0.9777777777777777,
      0.9777777777777777,
      0.9777777777777777,
      0.9777777777777777,
      0.9777777777777777,
      0.9777777777777777,
      0.9777777777777777,
      0.9777777777777777,
      0.9777777777777777,
      0.9777777777777777,
      0.9777777777777777,
      0.9333333333333333,
      0.9333333333333333,
      0.9333333333333333,
      0.9333333333333333
    ],
    "mt": [
      NaN,
      NaN,
      NaN,
      NaN,
      NaN,
      NaN,
      NaN,
      NaN,
      NaN,
      NaN,
      NaN,
      NaN,
      NaN,
      NaN,
      NaN,
      NaN,
      NaN,
      NaN,
      2.0,
      2.0,
      2.0,
      1.0,
      1.0,
      1.0,
      1.0,
      1.0,
      1.0,
      1.0,
      1.0,
      1.0,
      1.0,
      1.0,
      1.0,
      1.0,
      1.0,
      1.0,
      0.0,
      0.0,
      0.0,
      0.0
    ],
    "faf": [
      NaN,
      NaN,
      NaN,
      NaN,
      NaN,
      NaN,
      NaN,
      NaN,
      NaN,
      NaN,
      NaN,
      NaN,
      NaN,
      NaN,
      NaN,
      NaN,
      NaN,
      NaN,
      1.5625,
      1.5625,
      1.5625,
      1.5625,
      1.5625,
      1.5625,
      1.5625,
      1.5625,
      1.5625,
      1.5625,
      1.5625,
      1.5625,
      1.5625,
      1.5625,
      1.5625,
      1.5625,
      1.5625,
      1.5625,
      1.5625,
      1.5625,
      1.5625,
      1.5625
    ],
    "ml": [
      NaN,
      NaN,
      NaN,
      NaN,
      NaN,
      NaN,
      NaN,
      NaN,
      NaN,
      NaN,
      NaN,
      NaN,
      NaN,
      NaN,
      NaN,
      NaN,
      NaN,
      NaN,
      0.0,
      0.0,
      1.0,
      2.0,
      2.0,
      2.0,
      2.0,
      2.0,
      2.0,
      2.0,
      2.0,
      2.0,
      2.0,
      2.0,
      2.0,
      2.0,
      2.0,
      2.0,
      3.0,
      3.0,
      3.0,
      3.0
    ],
    "gt": [
      NaN,
      NaN,
      NaN,
      NaN,
      NaN,
      NaN,
      NaN,
      NaN,
      NaN,
      NaN,
      NaN,
      NaN,
      NaN,
      NaN,
      NaN,
      NaN,
      NaN,
      NaN,
      86.0,
      86.0,
      86.0,
      86.0,
      86.0,
      86.0,
      86.0,
      86.0,
      86.0,
      86.0,
      86.0,
      86.0,
      86.0,
      86.0,
      86.0,
      86.0,
      86.0,
      86.0,
      86.0,
      86.0,
      86.0,
      86.0
    ],
    "mota": [
      NaN,
      NaN,
      NaN,
      NaN,
      NaN,
      NaN,
      NaN,
      NaN,
      NaN,
      NaN,
      NaN,
      NaN,
      NaN,
      NaN,
      NaN,
      NaN,
      NaN,
      NaN,
      0.5813953488372092,
      0.5813953488372092,
      0.5348837209302326,
      0.5116279069767442,
      0.5116279069767442,
      0.5116279069767442,
      0.5116279069767442,
      0.5116279069767442,
      0.5116279069767442,
      0.5116279069767442,
      0.5116279069767442,
      0.5116279069767442,
      0.5116279069767442,
      0.5116279069767442,
      0.5116279069767442,
      0.5116279069767442,
      0.5116279069767442,
      0.5116279069767442,
      0.16279069767441856,
      0.16279069767441856,
      0.16279069767441856,
      0.16279069767441856
    ],
    "motp": [
      NaN,
      NaN,
      NaN,
      NaN,
      NaN,
      NaN,
      NaN,
      NaN,
      NaN,
      NaN,
      NaN,
      NaN,
      NaN,
      NaN,
      NaN,
      NaN,
      NaN,
      NaN,
      0.6825197086130472,
      0.6825197086130472,
      0.6961980900763596,
      0.6768464269298382,
      0.6768464269298382,
      0.6768464269298382,
      0.6768464269298382,
      0.6768464269298382,
      0.6768464269298382,
      0.6768464269298382,
      0.6768464269298382,
      0.6768464269298382,
      0.6768464269298382,
      0.6768464269298382,
      0.6768464269298382,
      0.6768464269298382,
      0.6768464269298382,
      0.6768464269298382,
      1.0658566437372206,
      1.0658566437372206,
      1.0658566437372206,
      1.0658566437372206
    ]
  },
  "car": {
    "confidence": [
      NaN,
      NaN,
      NaN,
      NaN,
      NaN,
      NaN,
      NaN,
      NaN,
      NaN,
      NaN,
      NaN,
      NaN,
      NaN,
      NaN,
      NaN,
      NaN,
      NaN,
      0.4631726723454897,
      0.5261135101318359,
      0.551101678609848,
      0.5786890800182636,
      0.607898160815239,
      0.6235145396656461,
      0.6414141637101937,
      0.6523708924651146,
      0.6602577444385079,
      0.6689779084661732,
      0.6773921533634788,
      0.6883164802018333,
      0.698503471556164,
      0.7072258591651917,
      0.7155417955440023,
      0.7169310439091462,
      0.727258796041662,
      0.7408836751964205,
      0.7612456253710642,
      0.7697789468617632,
      0.7717499686673448,
      0.7849644476631509,
      0.8072978167728286
    ],
    "recall_hypo": [
      1.0,
      0.976923076923,
      0.953846153846,
      0.930769230769,
      0.907692307692,
      0.884615384615,
      0.861538461538,
      0.838461538462,
      0.815384615385,
      0.792307692308,
      0.769230769231,
      0.746153846154,
      0.723076923077,
      0.7,
      0.676923076923,
      0.653846153846,
      0.630769230769,
      0.607692307692,
      0.584615384615,
      0.561538461538,
      0.538461538462,
      0.515384615385,
      0.492307692308,
      0.469230769231,
      0.446153846154,
      0.423076923077,
      0.4,
      0.376923076923,
      0.353846153846,
      0.330769230769,
      0.307692307692,
      0.284615384615,
      0.261538461538,
      0.238461538462,
      0.215384615385,
      0.192307692308,
      0.169230769231,
      0.146153846154,
      0.123076923077,
      0.1
    ],
    "lgd": [
      NaN,
      NaN,
      NaN,
      NaN,
      NaN,
      NaN,
      NaN,
      NaN,
      NaN,
      NaN,
      NaN,
      NaN,
      NaN,
      NaN,
      NaN,
      NaN,
      NaN,
      2.0866141732283463,
      2.3151260504201683,
      2.4955357142857144,
      2.6333333333333333,
      2.7938144329896906,
      2.9782608695652173,
      3.218390804597701,
      3.432926829268293,
      3.6455696202531644,
      3.7708333333333335,
      3.792307692307692,
      4.024193548387097,
      4.0636363636363635,
      4.114583333333333,
      4.333333333333333,
      4.267441860465116,
      4.285714285714286,
      4.125,
      4.293103448275862,
      4.56,
      4.913043478260869,
      5.275,
      5.7
    ],
    "frag": [
      NaN,
      NaN,
      NaN,
      NaN,
      NaN,
      NaN,
      NaN,
      NaN,
      NaN,
      NaN,
      NaN,
      NaN,
      NaN,
      NaN,
      NaN,
      NaN,
      NaN,
      70.0,
      55.0,
      44.0,
      37.0,
      32.0,
      29.0,
      21.0,
      19.0,
      15.0,
      11.0,
      10.0,
      9.0,
      6.0,
      6.0,
      5.0,
      5.0,
      5.0,
      3.0,
      2.0,
      1.0,
      1.0,
      1.0,
      1.0
    ],
    "recall": [
      NaN,
      NaN,
      NaN,
      NaN,
      NaN,
      NaN,
      NaN,
      NaN,
      NaN,
      NaN,
      NaN,
      NaN,
      NaN,
      NaN,
      NaN,
      NaN,
      NaN,
      0.6456577500916086,
      0.6203737632832539,
      0.5928911689263466,
      0.5665078783437156,
      0.537925980212532,
      0.5163063393184316,
      0.4902894833272261,
      0.46353975815316967,
      0.44155368266764383,
      0.419567607182118,
      0.39171857823378525,
      0.3708318065225357,
      0.34224990839135216,
      0.3169659215829974,
      0.2938805423231953,
      0.27629168193477466,
      0.24624404543788933,
      0.21986075485525833,
      0.2052033711982411,
      0.17808721143275924,
      0.15866617808721142,
      0.13228288750458042,
      0.105533162330524
    ],
    "tid": [
      NaN,
      NaN,
      NaN,
      NaN,
      NaN,
      NaN,
      NaN,
      NaN,
      NaN,
      NaN,
      NaN,
      NaN,
      NaN,
      NaN,
      NaN,
      NaN,
      NaN,
      1.531496062992126,
      1.6596638655462186,
      1.8125,
      1.7809523809523808,
      1.7783505154639174,
      1.9728260869565217,
      2.045977011494253,
      2.2804878048780486,
      2.2911392405063293,
      2.2847222222222223,
      2.146153846153846,
      2.338709677419355,
      2.209090909090909,
      2.03125,
      2.033333333333333,
      1.8604651162790697,
      1.9428571428571428,
      1.53125,
      1.4310344827586208,
      1.68,
      1.8043478260869565,
      1.7,
      1.8
    ],
    "fn": [
      NaN,
      NaN,
      NaN,
      NaN,
      NaN,
      NaN,
      NaN,
      NaN,
      NaN,
      NaN,
      NaN,
      NaN,
      NaN,
      NaN,
      NaN,
      NaN,
      NaN,
      967.0,
      1036.0,
      1111.0,
      1183.0,
      1261.0,
      1320.0,
      1391.0,
      1464.0,
      1524.0,
      1584.0,
      1660.0,
      1717.0,
      1795.0,
      1864.0,
      1927.0,
      1975.0,
      2057.0,
      2129.0,
      2169.0,
      2243.0,
      2296.0,
      2368.0,
      2441.0
    ],
    "fp": [
      NaN,
      NaN,
      NaN,
      NaN,
      NaN,
      NaN,
      NaN,
      NaN,
      NaN,
      NaN,
      NaN,
      NaN,
      NaN,
      NaN,
      NaN,
      NaN,
      NaN,
      132.0,
      119.0,
      101.0,
      88.0,
      82.0,
      79.0,
      71.0,
      68.0,
      65.0,
      60.0,
      58.0,
      55.0,
      45.0,
      37.0,
      36.0,
      36.0,
      30.0,
      30.0,
      29.0,
      25.0,
      15.0,
      14.0,
      14.0
    ],
    "tp": [
      NaN,
      NaN,
      NaN,
      NaN,
      NaN,
      NaN,
      NaN,
      NaN,
      NaN,
      NaN,
      NaN,
      NaN,
      NaN,
      NaN,
      NaN,
      NaN,
      NaN,
      1669.0,
      1616.0,
      1553.0,
      1492.0,
      1425.0,
      1373.0,
      1311.0,
      1241.0,
      1184.0,
      1129.0,
      1053.0,
      1000.0,
      925.0,
      856.0,
      794.0,
      746.0,
      664.0,
      596.0,
      556.0,
      484.0,
      431.0,
      359.0,
      286.0
    ],
    "ids": [
      NaN,
      NaN,
      NaN,
      NaN,
      NaN,
      NaN,
      NaN,
      NaN,
      NaN,
      NaN,
      NaN,
      NaN,
      NaN,
      NaN,
      NaN,
      NaN,
      NaN,
      93.0,
      77.0,
      65.0,
      54.0,
      43.0,
      36.0,
      27.0,
      24.0,
      21.0,
      16.0,
      16.0,
      12.0,
      9.0,
      9.0,
      8.0,
      8.0,
      8.0,
      4.0,
      4.0,
      2.0,
      2.0,
      2.0,
      2.0
    ],
    "motar": [
      NaN,
      NaN,
      NaN,
      NaN,
      NaN,
      NaN,
      NaN,
      NaN,
      NaN,
      NaN,
      NaN,
      NaN,
      NaN,
      NaN,
      NaN,
      NaN,
      NaN,
      0.9209107249850211,
      0.9263613861386139,
      0.9349645846748229,
      0.9410187667560324,
      0.9424561403508772,
      0.942461762563729,
      0.9458428680396646,
      0.945205479452055,
      0.9451013513513513,
      0.9468556244464128,
      0.9449192782526116,
      0.945,
      0.9513513513513514,
      0.9567757009345794,
      0.9546599496221663,
      0.9517426273458445,
      0.9548192771084337,
      0.9496644295302014,
      0.947841726618705,
      0.9483471074380165,
      0.9651972157772621,
      0.9610027855153204,
      0.951048951048951
    ],
    "mt": [
      NaN,
      NaN,
      NaN,
      NaN,
      NaN,
      NaN,
      NaN,
      NaN,
      NaN,
      NaN,
      NaN,
      NaN,
      NaN,
      NaN,
      NaN,
      NaN,
      NaN,
      57.0,
      53.0,
      51.0,
      47.0,
      43.0,
      37.0,
      37.0,
      32.0,
      30.0,
      28.0,
      25.0,
      23.0,
      20.0,
      18.0,
      17.0,
      17.0,
      14.0,
      13.0,
      13.0,
      12.0,
      10.0,
      8.0,
      6.0
    ],
    "faf": [
      NaN,
      NaN,
      NaN,
      NaN,
      NaN,
      NaN,
      NaN,
      NaN,
      NaN,
      NaN,
      NaN,
      NaN,
      NaN,
      NaN,
      NaN,
      NaN,
      NaN,
      81.48148148148148,
      73.4567901234568,
      62.34567901234568,
      54.32098765432099,
      50.617283950617285,
      48.76543209876543,
      43.82716049382716,
      41.9753086419753,
      40.123456790123456,
      37.03703703703704,
      35.80246913580247,
      33.95061728395062,
      27.77777777777778,
      22.839506172839506,
      22.22222222222222,
      22.22222222222222,
      18.51851851851852,
      18.51851851851852,
      17.901234567901234,
      15.432098765432098,
      9.25925925925926,
      8.641975308641975,
      8.641975308641975
    ],
    "ml": [
      NaN,
      NaN,
      NaN,
      NaN,
      NaN,
      NaN,
      NaN,
      NaN,
      NaN,
      NaN,
      NaN,
      NaN,
      NaN,
      NaN,
      NaN,
      NaN,
      NaN,
      32.0,
      40.0,
      47.0,
      52.0,
      59.0,
      66.0,
      73.0,
      80.0,
      85.0,
      91.0,
      97.0,
      100.0,
      105.0,
      111.0,
      115.0,
      117.0,
      123.0,
      127.0,
      130.0,
      133.0,
      135.0,
      138.0,
      141.0
    ],
    "gt": [
      NaN,
      NaN,
      NaN,
      NaN,
      NaN,
      NaN,
      NaN,
      NaN,
      NaN,
      NaN,
      NaN,
      NaN,
      NaN,
      NaN,
      NaN,
      NaN,
      NaN,
      2729.0,
      2729.0,
      2729.0,
      2729.0,
      2729.0,
      2729.0,
      2729.0,
      2729.0,
      2729.0,
      2729.0,
      2729.0,
      2729.0,
      2729.0,
      2729.0,
      2729.0,
      2729.0,
      2729.0,
      2729.0,
      2729.0,
      2729.0,
      2729.0,
      2729.0,
      2729.0
    ],
    "mota": [
      NaN,
      NaN,
      NaN,
      NaN,
      NaN,
      NaN,
      NaN,
      NaN,
      NaN,
      NaN,
      NaN,
      NaN,
      NaN,
      NaN,
      NaN,
      NaN,
      NaN,
      0.5632099670208868,
      0.5485525833638696,
      0.5320630267497252,
      0.5144741663613045,
      0.4921216562843532,
      0.4741663613045072,
      0.4543788933675339,
      0.42982777574203,
      0.41004030780505685,
      0.3917185782337853,
      0.36460241846830344,
      0.3462806888970319,
      0.3224624404543789,
      0.3001099303774276,
      0.27775742030047634,
      0.2601685599120557,
      0.23231953096372293,
      0.20740197874679367,
      0.19311102968120186,
      0.1681934774642726,
      0.15243679003297916,
      0.12641993404177354,
      0.09967020886771716
    ],
    "motp": [
      NaN,
      NaN,
      NaN,
      NaN,
      NaN,
      NaN,
      NaN,
      NaN,
      NaN,
      NaN,
      NaN,
      NaN,
      NaN,
      NaN,
      NaN,
      NaN,
      NaN,
      0.406021425866928,
      0.39860609375126316,
      0.3919289602866009,
      0.38802988984175385,
      0.3834662867482417,
      0.373055727250914,
      0.36292120468033795,
      0.3537046974022043,
      0.3495242035340571,
      0.34797465028644364,
      0.34695706034357887,
      0.34883929858012663,
      0.35061960790253,
      0.3478945560142274,
      0.3331837421176608,
      0.33229179288772354,
      0.3153292313709199,
      0.3061830993446107,
      0.3038758374530757,
      0.2961612593713358,
      0.3046914420785017,
      0.3209927376787535,
      0.3249650952496841
    ]
  },
  "motorcycle": {
    "confidence": [
      NaN,
      NaN,
      NaN,
      NaN,
      NaN,
      NaN,
      NaN,
      NaN,
      NaN,
      NaN,
      NaN,
      NaN,
      NaN,
      NaN,
      NaN,
      NaN,
      NaN,
      NaN,
      NaN,
      NaN,
      NaN,
      NaN,
      NaN,
      NaN,
      NaN,
      0.47698687590067973,
      0.6097053932872686,
      0.6298822950233113,
      0.6775355736414591,
      0.6775355736414591,
      0.785772825153846,
      0.785772825153846,
      0.785772825153846,
      0.7960445338095238,
      0.7960445338095238,
      0.7960445338095238,
      0.814022688517967,
      0.8209079392592592,
      0.8209079392592592,
      0.8209079392592592
    ],
    "recall_hypo": [
      1.0,
      0.976923076923,
      0.953846153846,
      0.930769230769,
      0.907692307692,
      0.884615384615,
      0.861538461538,
      0.838461538462,
      0.815384615385,
      0.792307692308,
      0.769230769231,
      0.746153846154,
      0.723076923077,
      0.7,
      0.676923076923,
      0.653846153846,
      0.630769230769,
      0.607692307692,
      0.584615384615,
      0.561538461538,
      0.538461538462,
      0.515384615385,
      0.492307692308,
      0.469230769231,
      0.446153846154,
      0.423076923077,
      0.4,
      0.376923076923,
      0.353846153846,
      0.330769230769,
      0.307692307692,
      0.284615384615,
      0.261538461538,
      0.238461538462,
      0.215384615385,
      0.192307692308,
      0.169230769231,
      0.146153846154,
      0.123076923077,
      0.1
    ],
    "lgd": [
      NaN,
      NaN,
      NaN,
      NaN,
      NaN,
      NaN,
      NaN,
      NaN,
      NaN,
      NaN,
      NaN,
      NaN,
      NaN,
      NaN,
      NaN,
      NaN,
      NaN,
      NaN,
      NaN,
      NaN,
      NaN,
      NaN,
      NaN,
      NaN,
      NaN,
      3.888888888888889,
      3.3125,
      3.3125,
      4.125,
      4.125,
      5.142857142857143,
      5.142857142857143,
      5.142857142857143,
      4.4,
      4.4,
      4.4,
      4.625,
      4.625,
      4.625,
      4.625
    ],
    "frag": [
      NaN,
      NaN,
      NaN,
      NaN,
      NaN,
      NaN,
      NaN,
      NaN,
      NaN,
      NaN,
      NaN,
      NaN,
      NaN,
      NaN,
      NaN,
      NaN,
      NaN,
      NaN,
      NaN,
      NaN,
      NaN,
      NaN,
      NaN,
      NaN,
      NaN,
      5.0,
      3.0,
      3.0,
      1.0,
      1.0,
      0.0,
      0.0,
      0.0,
      0.0,
      0.0,
      0.0,
      0.0,
      0.0,
      0.0,
      0.0
    ],
    "recall": [
      NaN,
      NaN,
      NaN,
      NaN,
      NaN,
      NaN,
      NaN,
      NaN,
      NaN,
      NaN,
      NaN,
      NaN,
      NaN,
      NaN,
      NaN,
      NaN,
      NaN,
      NaN,
      NaN,
      NaN,
      NaN,
      NaN,
      NaN,
      NaN,
      NaN,
      0.4495798319327731,
      0.41596638655462187,
      0.41596638655462187,
      0.36554621848739494,
      0.36554621848739494,
      0.31092436974789917,
      0.31092436974789917,
      0.31092436974789917,
      0.25630252100840334,
      0.25630252100840334,
      0.25630252100840334,
      0.16806722689075632,
      0.16806722689075632,
      0.16806722689075632,
      0.16806722689075632
    ],
    "tid": [
      NaN,
      NaN,
      NaN,
      NaN,
      NaN,
      NaN,
      NaN,
      NaN,
      NaN,
      NaN,
      NaN,
      NaN,
      NaN,
      NaN,
      NaN,
      NaN,
      NaN,
      NaN,
      NaN,
      NaN,
      NaN,
      NaN,
      NaN,
      NaN,
      NaN,
      3.3333333333333335,
      2.375,
      2.375,
      2.5,
      2.5,
      2.5,
      2.5,
      2.5,
      2.2,
      2.2,
      2.2,
      1.875,
      1.875,
      1.875,
      1.875
    ],
    "fn": [
      NaN,
      NaN,
      NaN,
      NaN,
      NaN,
      NaN,
      NaN,
      NaN,
      NaN,
      NaN,
      NaN,
      NaN,
      NaN,
      NaN,
      NaN,
      NaN,
      NaN,
      NaN,
      NaN,
      NaN,
      NaN,
      NaN,
      NaN,
      NaN,
      NaN,
      131.0,
      139.0,
      139.0,
      151.0,
      151.0,
      164.0,
      164.0,
      164.0,
      177.0,
      177.0,
      177.0,
      198.0,
      198.0,
      198.0,
      198.0
    ],
    "fp": [
      NaN,
      NaN,
      NaN,
      NaN,
      NaN,
      NaN,
      NaN,
      NaN,
      NaN,
      NaN,
      NaN,
      NaN,
      NaN,
      NaN,
      NaN,
      NaN,
      NaN,
      NaN,
      NaN,
      NaN,
      NaN,
      NaN,
      NaN,
      NaN,
      NaN,
      7.0,
      2.0,
      2.0,
      2.0,
      2.0,
      2.0,
      2.0,
      2.0,
      2.0,
      2.0,
      2.0,
      2.0,
      2.0,
      2.0,
      2.0
    ],
    "tp": [
      NaN,
      NaN,
      NaN,
      NaN,
      NaN,
      NaN,
      NaN,
      NaN,
      NaN,
      NaN,
      NaN,
      NaN,
      NaN,
      NaN,
      NaN,
      NaN,
      NaN,
      NaN,
      NaN,
      NaN,
      NaN,
      NaN,
      NaN,
      NaN,
      NaN,
      101.0,
      96.0,
      96.0,
      86.0,
      86.0,
      74.0,
      74.0,
      74.0,
      61.0,
      61.0,
      61.0,
      40.0,
      40.0,
      40.0,
      40.0
    ],
    "ids": [
      NaN,
      NaN,
      NaN,
      NaN,
      NaN,
      NaN,
      NaN,
      NaN,
      NaN,
      NaN,
      NaN,
      NaN,
      NaN,
      NaN,
      NaN,
      NaN,
      NaN,
      NaN,
      NaN,
      NaN,
      NaN,
      NaN,
      NaN,
      NaN,
      NaN,
      6.0,
      3.0,
      3.0,
      1.0,
      1.0,
      0.0,
      0.0,
      0.0,
      0.0,
      0.0,
      0.0,
      0.0,
      0.0,
      0.0,
      0.0
    ],
    "motar": [
      NaN,
      NaN,
      NaN,
      NaN,
      NaN,
      NaN,
      NaN,
      NaN,
      NaN,
      NaN,
      NaN,
      NaN,
      NaN,
      NaN,
      NaN,
      NaN,
      NaN,
      NaN,
      NaN,
      NaN,
      NaN,
      NaN,
      NaN,
      NaN,
      NaN,
      0.9306930693069306,
      0.9791666666666666,
      0.9791666666666666,
      0.9767441860465116,
      0.9767441860465116,
      0.972972972972973,
      0.972972972972973,
      0.972972972972973,
      0.9672131147540983,
      0.9672131147540983,
      0.9672131147540983,
      0.9499999999999993,
      0.9499999999999993,
      0.9499999999999993,
      0.9499999999999993
    ],
    "mt": [
      NaN,
      NaN,
      NaN,
      NaN,
      NaN,
      NaN,
      NaN,
      NaN,
      NaN,
      NaN,
      NaN,
      NaN,
      NaN,
      NaN,
      NaN,
      NaN,
      NaN,
      NaN,
      NaN,
      NaN,
      NaN,
      NaN,
      NaN,
      NaN,
      NaN,
      1.0,
      1.0,
      1.0,
      1.0,
      1.0,
      1.0,
      1.0,
      1.0,
      1.0,
      1.0,
      1.0,
      1.0,
      1.0,
      1.0,
      1.0
    ],
    "faf": [
      NaN,
      NaN,
      NaN,
      NaN,
      NaN,
      NaN,
      NaN,
      NaN,
      NaN,
      NaN,
      NaN,
      NaN,
      NaN,
      NaN,
      NaN,
      NaN,
      NaN,
      NaN,
      NaN,
      NaN,
      NaN,
      NaN,
      NaN,
      NaN,
      NaN,
      11.11111111111111,
      3.1746031746031744,
      3.1746031746031744,
      3.1746031746031744,
      3.1746031746031744,
      3.1746031746031744,
      3.1746031746031744,
      3.1746031746031744,
      3.1746031746031744,
      3.1746031746031744,
      3.1746031746031744,
      3.1746031746031744,
      3.1746031746031744,
      3.1746031746031744,
      3.1746031746031744
    ],
    "ml": [
      NaN,
      NaN,
      NaN,
      NaN,
      NaN,
      NaN,
      NaN,
      NaN,
      NaN,
      NaN,
      NaN,
      NaN,
      NaN,
      NaN,
      NaN,
      NaN,
      NaN,
      NaN,
      NaN,
      NaN,
      NaN,
      NaN,
      NaN,
      NaN,
      NaN,
      4.0,
      4.0,
      4.0,
      6.0,
      6.0,
      7.0,
      7.0,
      7.0,
      8.0,
      8.0,
      8.0,
      9.0,
      9.0,
      9.0,
      9.0
    ],
    "gt": [
      NaN,
      NaN,
      NaN,
      NaN,
      NaN,
      NaN,
      NaN,
      NaN,
      NaN,
      NaN,
      NaN,
      NaN,
      NaN,
      NaN,
      NaN,
      NaN,
      NaN,
      NaN,
      NaN,
      NaN,
      NaN,
      NaN,
      NaN,
      NaN,
      NaN,
      238.0,
      238.0,
      238.0,
      238.0,
      238.0,
      238.0,
      238.0,
      238.0,
      238.0,
      238.0,
      238.0,
      238.0,
      238.0,
      238.0,
      238.0
    ],
    "mota": [
      NaN,
      NaN,
      NaN,
      NaN,
      NaN,
      NaN,
      NaN,
      NaN,
      NaN,
      NaN,
      NaN,
      NaN,
      NaN,
      NaN,
      NaN,
      NaN,
      NaN,
      NaN,
      NaN,
      NaN,
      NaN,
      NaN,
      NaN,
      NaN,
      NaN,
      0.39495798319327735,
      0.39495798319327735,
      0.39495798319327735,
      0.3529411764705882,
      0.3529411764705882,
      0.3025210084033614,
      0.3025210084033614,
      0.3025210084033614,
      0.24789915966386555,
      0.24789915966386555,
      0.24789915966386555,
      0.15966386554621848,
      0.15966386554621848,
      0.15966386554621848,
      0.15966386554621848
    ],
    "motp": [
      NaN,
      NaN,
      NaN,
      NaN,
      NaN,
      NaN,
      NaN,
      NaN,
      NaN,
      NaN,
      NaN,
      NaN,
      NaN,
      NaN,
      NaN,
      NaN,
      NaN,
      NaN,
      NaN,
      NaN,
      NaN,
      NaN,
      NaN,
      NaN,
      NaN,
      0.5460556242638165,
      0.49774392979752563,
      0.49774392979752563,
      0.5027145761431938,
      0.5027145761431938,
      0.5279786595804868,
      0.5279786595804868,
      0.5279786595804868,
      0.553320777473698,
      0.553320777473698,
      0.553320777473698,
      0.5499120888960187,
      0.5499120888960187,
      0.5499120888960187,
      0.5499120888960187
    ]
  },
  "pedestrian": {
    "confidence": [
      NaN,
      NaN,
      NaN,
      NaN,
      NaN,
      NaN,
      NaN,
      NaN,
      NaN,
      NaN,
      NaN,
      NaN,
      NaN,
      NaN,
      NaN,
      0.4556661809867624,
      0.49576038636734004,
      0.5153590857982635,
      0.5444055627861341,
      0.5514769032597542,
      0.5627995323051106,
      0.5690308894429889,
      0.5812459525765992,
      0.5914830054555621,
      0.5946368319647652,
      0.6029420703649521,
      0.6077445450523885,
      0.6137222290039063,
      0.6228157669504958,
      0.6289241115252177,
      0.6436980068683624,
      0.6529076796668402,
      0.6633901999999999,
      0.664910565592913,
      0.6660012180606524,
      0.6744476061937096,
      0.6797506193057485,
      0.6906690398635864,
      0.7127740794269561,
      0.7322292104363441
    ],
    "recall_hypo": [
      1.0,
      0.976923076923,
      0.953846153846,
      0.930769230769,
      0.907692307692,
      0.884615384615,
      0.861538461538,
      0.838461538462,
      0.815384615385,
      0.792307692308,
      0.769230769231,
      0.746153846154,
      0.723076923077,
      0.7,
      0.676923076923,
      0.653846153846,
      0.630769230769,
      0.607692307692,
      0.584615384615,
      0.561538461538,
      0.538461538462,
      0.515384615385,
      0.492307692308,
      0.469230769231,
      0.446153846154,
      0.423076923077,
      0.4,
      0.376923076923,
      0.353846153846,
      0.330769230769,
      0.307692307692,
      0.284615384615,
      0.261538461538,
      0.238461538462,
      0.215384615385,
      0.192307692308,
      0.169230769231,
      0.146153846154,
      0.123076923077,
      0.1
    ],
    "lgd": [
      NaN,
      NaN,
      NaN,
      NaN,
      NaN,
      NaN,
      NaN,
      NaN,
      NaN,
      NaN,
      NaN,
      NaN,
      NaN,
      NaN,
      NaN,
      0.9863013698630136,
      1.0704225352112675,
      1.044776119402985,
      1.1846153846153846,
      1.2230769230769232,
      1.3984375,
      1.4841269841269842,
      1.5666666666666667,
      1.8305084745762712,
      1.9827586206896552,
      2.146551724137931,
      2.353448275862069,
      2.543103448275862,
      2.8189655172413794,
      3.1293103448275863,
      3.25,
      3.5,
      3.69811320754717,
      3.875,
      4.086538461538462,
      4.186274509803922,
      4.5638297872340425,
      4.6395348837209305,
      5.243243243243243,
      5.048387096774194
    ],
    "frag": [
      NaN,
      NaN,
      NaN,
      NaN,
      NaN,
      NaN,
      NaN,
      NaN,
      NaN,
      NaN,
      NaN,
      NaN,
      NaN,
      NaN,
      NaN,
      30.0,
      24.0,
      25.0,
      31.0,
      34.0,
      33.0,
      34.0,
      31.0,
      33.0,
      34.0,
      37.0,
      37.0,
      41.0,
      44.0,
      38.0,
      42.0,
      35.0,
      33.0,
      33.0,
      31.0,
      26.0,
      23.0,
      18.0,
      9.0,
      5.0
    ],
    "recall": [
      NaN,
      NaN,
      NaN,
      NaN,
      NaN,
      NaN,
      NaN,
      NaN,
      NaN,
      NaN,
      NaN,
      NaN,
      NaN,
      NaN,
      NaN,
      0.8013605442176871,
      0.7863945578231293,
      0.7700680272108843,
      0.7462585034013606,
      0.7387755102040816,
      0.7210884353741497,
      0.7020408163265306,
      0.682312925170068,
      0.6551020408163265,
      0.6374149659863946,
      0.6068027210884354,
      0.580952380952381,
      0.5598639455782313,
      0.5346938775510204,
      0.5102040816326531,
      0.4897959183673469,
      0.43945578231292515,
      0.41020408163265304,
      0.3891156462585034,
      0.37551020408163266,
      0.3360544217687075,
      0.3013605442176871,
      0.24557823129251702,
      0.20272108843537415,
      0.17755102040816326
    ],
    "tid": [
      NaN,
      NaN,
      NaN,
      NaN,
      NaN,
      NaN,
      NaN,
      NaN,
      NaN,
      NaN,
      NaN,
      NaN,
      NaN,
      NaN,
      NaN,
      0.6301369863013698,
      0.676056338028169,
      0.664179104477612,
      0.7,
      0.7307692307692307,
      0.796875,
      0.8888888888888888,
      0.8666666666666667,
      0.9067796610169492,
      0.9310344827586207,
      1.0603448275862069,
      1.2241379310344827,
      1.3879310344827587,
      1.5172413793103448,
      1.5344827586206897,
      1.5344827586206897,
      1.6481481481481481,
      1.6981132075471699,
      1.8076923076923077,
      1.8653846153846154,
      1.911764705882353,
      2.0531914893617023,
      1.7790697674418605,
      1.864864864864865,
      2.096774193548387
    ],
    "fn": [
      NaN,
      NaN,
      NaN,
      NaN,
      NaN,
      NaN,
      NaN,
      NaN,
      NaN,
      NaN,
      NaN,
      NaN,
      NaN,
      NaN,
      NaN,
      292.0,
      314.0,
      338.0,
      373.0,
      384.0,
      410.0,
      438.0,
      467.0,
      507.0,
      533.0,
      578.0,
      616.0,
      647.0,
      684.0,
      720.0,
      750.0,
      824.0,
      867.0,
      898.0,
      918.0,
      976.0,
      1027.0,
      1109.0,
      1172.0,
      1209.0
    ],
    "fp": [
      NaN,
      NaN,
      NaN,
      NaN,
      NaN,
      NaN,
      NaN,
      NaN,
      NaN,
      NaN,
      NaN,
      NaN,
      NaN,
      NaN,
      NaN,
      1508.0,
      1287.0,
      1184.0,
      1025.0,
      957.0,
      886.0,
      827.0,
      696.0,
      642.0,
      596.0,
      517.0,
      485.0,
      429.0,
      342.0,
      303.0,
      233.0,
      205.0,
      180.0,
      176.0,
      153.0,
      136.0,
      116.0,
      85.0,
      61.0,
      49.0
    ],
    "tp": [
      NaN,
      NaN,
      NaN,
      NaN,
      NaN,
      NaN,
      NaN,
      NaN,
      NaN,
      NaN,
      NaN,
      NaN,
      NaN,
      NaN,
      NaN,
      969.0,
      968.0,
      952.0,
      937.0,
      932.0,
      915.0,
      892.0,
      874.0,
      841.0,
      817.0,
      786.0,
      750.0,
      724.0,
      693.0,
      665.0,
      643.0,
      582.0,
      544.0,
      513.0,
      498.0,
      452.0,
      403.0,
      332.0,
      277.0,
      247.0
    ],
    "ids": [
      NaN,
      NaN,
      NaN,
      NaN,
      NaN,
      NaN,
      NaN,
      NaN,
      NaN,
      NaN,
      NaN,
      NaN,
      NaN,
      NaN,
      NaN,
      209.0,
      188.0,
      180.0,
      160.0,
      154.0,
      145.0,
      140.0,
      129.0,
      122.0,
      120.0,
      106.0,
      104.0,
      99.0,
      93.0,
      85.0,
      77.0,
      64.0,
      59.0,
      59.0,
      54.0,
      42.0,
      40.0,
      29.0,
      21.0,
      14.0
    ],
    "motar": [
      NaN,
      NaN,
      NaN,
      NaN,
      NaN,
      NaN,
      NaN,
      NaN,
      NaN,
      NaN,
      NaN,
      NaN,
      NaN,
      NaN,
      NaN,
      0.0,
      0.0,
      0.0,
      0.0,
      0.0,
      0.031693989071038264,
      0.07286995515695072,
      0.2036613272311213,
      0.23662306777645659,
      0.2705018359853121,
      0.34223918575063617,
      0.3533333333333334,
      0.4074585635359115,
      0.5064935064935066,
      0.5443609022556393,
      0.6376360808709174,
      0.6477663230240549,
      0.6691176470588238,
      0.6569200779727096,
      0.6927710843373491,
      0.6991150442477876,
      0.7121588089330024,
      0.7439759036144578,
      0.779783393501805,
      0.8016194331983806
    ],
    "mt": [
      NaN,
      NaN,
      NaN,
      NaN,
      NaN,
      NaN,
      NaN,
      NaN,
      NaN,
      NaN,
      NaN,
      NaN,
      NaN,
      NaN,
      NaN,
      54.0,
      52.0,
      51.0,
      48.0,
      46.0,
      40.0,
      38.0,
      35.0,
      31.0,
      29.0,
      26.0,
      26.0,
      25.0,
      21.0,
      19.0,
      17.0,
      17.0,
      15.0,
      14.0,
      14.0,
      14.0,
      11.0,
      9.0,
      8.0,
      8.0
    ],
    "faf": [
      NaN,
      NaN,
      NaN,
      NaN,
      NaN,
      NaN,
      NaN,
      NaN,
      NaN,
      NaN,
      NaN,
      NaN,
      NaN,
      NaN,
      NaN,
      1125.3731343283582,
      960.4477611940299,
      890.2255639097743,
      770.6766917293234,
      719.5488721804511,
      666.1654135338347,
      621.8045112781955,
      523.3082706766918,
      486.3636363636363,
      451.51515151515156,
      391.66666666666663,
      367.42424242424244,
      327.48091603053433,
      261.0687022900764,
      231.29770992366412,
      177.86259541984734,
      156.4885496183206,
      137.40458015267177,
      134.35114503816794,
      116.79389312977099,
      103.81679389312977,
      88.54961832061069,
      65.38461538461539,
      46.92307692307692,
      37.69230769230769
    ],
    "ml": [
      NaN,
      NaN,
      NaN,
      NaN,
      NaN,
      NaN,
      NaN,
      NaN,
      NaN,
      NaN,
      NaN,
      NaN,
      NaN,
      NaN,
      NaN,
      15.0,
      17.0,
      20.0,
      22.0,
      22.0,
      23.0,
      24.0,
      27.0,
      28.0,
      29.0,
      29.0,
      30.0,
      32.0,
      32.0,
      33.0,
      34.0,
      38.0,
      41.0,
      43.0,
      44.0,
      48.0,
      51.0,
      55.0,
      60.0,
      64.0
    ],
    "gt": [
      NaN,
      NaN,
      NaN,
      NaN,
      NaN,
      NaN,
      NaN,
      NaN,
      NaN,
      NaN,
      NaN,
      NaN,
      NaN,
      NaN,
      NaN,
      1470.0,
      1470.0,
      1470.0,
      1470.0,
      1470.0,
      1470.0,
      1470.0,
      1470.0,
      1470.0,
      1470.0,
      1470.0,
      1470.0,
      1470.0,
      1470.0,
      1470.0,
      1470.0,
      1470.0,
      1470.0,
      1470.0,
      1470.0,
      1470.0,
      1470.0,
      1470.0,
      1470.0,
      1470.0
    ],
    "mota": [
      NaN,
      NaN,
      NaN,
      NaN,
      NaN,
      NaN,
      NaN,
      NaN,
      NaN,
      NaN,
      NaN,
      NaN,
      NaN,
      NaN,
      NaN,
      0.0,
      0.0,
      0.0,
      0.0,
      0.0,
      0.019727891156462563,
      0.04421768707482998,
      0.1210884353741497,
      0.13537414965986394,
      0.15034013605442176,
      0.1829931972789116,
      0.1802721088435374,
      0.20068027210884354,
      0.2387755102040816,
      0.24625850340136057,
      0.2789115646258503,
      0.25646258503401365,
      0.24761904761904763,
      0.22925170068027212,
      0.23469387755102045,
      0.21496598639455777,
      0.1952380952380952,
      0.1680272108843538,
      0.14693877551020407,
      0.13469387755102036
    ],
    "motp": [
      NaN,
      NaN,
      NaN,
      NaN,
      NaN,
      NaN,
      NaN,
      NaN,
      NaN,
      NaN,
      NaN,
      NaN,
      NaN,
      NaN,
      NaN,
      0.7313181213529867,
      0.7285105629669589,
      0.7375003324492863,
      0.7369975861883359,
      0.7440556680790861,
      0.7500928709204847,
      0.7661686608996672,
      0.8023997239811369,
      0.810085447893224,
      0.8142362177573099,
      0.801461324294736,
      0.8029135478317624,
      0.8187495718066848,
      0.8161933469300144,
      0.8297498465249646,
      0.8252920830448176,
      0.8194679042291327,
      0.7980879043879968,
      0.8182719412238442,
      0.8081971707635905,
      0.7888014087652135,
      0.8310361817062358,
      0.7787446657508144,
      0.769912322702719,
      0.7590106631552513
    ]
  },
  "trailer": {
    "confidence": [
      NaN,
      NaN,
      NaN,
      NaN,
      NaN,
      NaN,
      NaN,
      NaN,
      NaN,
      NaN,
      NaN,
      NaN,
      NaN,
      NaN,
      NaN,
      NaN,
      NaN,
      NaN,
      NaN,
      NaN,
      NaN,
      NaN,
      NaN,
      NaN,
      NaN,
      NaN,
      NaN,
      NaN,
      NaN,
      NaN,
      NaN,
      NaN,
      NaN,
      NaN,
      NaN,
      NaN,
      NaN,
      NaN,
      NaN,
      NaN
    ],
    "recall_hypo": [
      NaN,
      NaN,
      NaN,
      NaN,
      NaN,
      NaN,
      NaN,
      NaN,
      NaN,
      NaN,
      NaN,
      NaN,
      NaN,
      NaN,
      NaN,
      NaN,
      NaN,
      NaN,
      NaN,
      NaN,
      NaN,
      NaN,
      NaN,
      NaN,
      NaN,
      NaN,
      NaN,
      NaN,
      NaN,
      NaN,
      NaN,
      NaN,
      NaN,
      NaN,
      NaN,
      NaN,
      NaN,
      NaN,
      NaN,
      NaN
    ],
    "lgd": [
      20,
      20,
      20,
      20,
      20,
      20,
      20,
      20,
      20,
      20,
      20,
      20,
      20,
      20,
      20,
      20,
      20,
      20,
      20,
      20,
      20,
      20,
      20,
      20,
      20,
      20,
      20,
      20,
      20,
      20,
      20,
      20,
      20,
      20,
      20,
      20,
      20,
      20,
      20,
      20
    ],
    "frag": [
      NaN,
      NaN,
      NaN,
      NaN,
      NaN,
      NaN,
      NaN,
      NaN,
      NaN,
      NaN,
      NaN,
      NaN,
      NaN,
      NaN,
      NaN,
      NaN,
      NaN,
      NaN,
      NaN,
      NaN,
      NaN,
      NaN,
      NaN,
      NaN,
      NaN,
      NaN,
      NaN,
      NaN,
      NaN,
      NaN,
      NaN,
      NaN,
      NaN,
      NaN,
      NaN,
      NaN,
      NaN,
      NaN,
      NaN,
      NaN
    ],
    "recall": [
      0.0,
      0.0,
      0.0,
      0.0,
      0.0,
      0.0,
      0.0,
      0.0,
      0.0,
      0.0,
      0.0,
      0.0,
      0.0,
      0.0,
      0.0,
      0.0,
      0.0,
      0.0,
      0.0,
      0.0,
      0.0,
      0.0,
      0.0,
      0.0,
      0.0,
      0.0,
      0.0,
      0.0,
      0.0,
      0.0,
      0.0,
      0.0,
      0.0,
      0.0,
      0.0,
      0.0,
      0.0,
      0.0,
      0.0,
      0.0
    ],
    "tid": [
      20,
      20,
      20,
      20,
      20,
      20,
      20,
      20,
      20,
      20,
      20,
      20,
      20,
      20,
      20,
      20,
      20,
      20,
      20,
      20,
      20,
      20,
      20,
      20,
      20,
      20,
      20,
      20,
      20,
      20,
      20,
      20,
      20,
      20,
      20,
      20,
      20,
      20,
      20,
      20
    ],
    "fn": [
      41,
      41,
      41,
      41,
      41,
      41,
      41,
      41,
      41,
      41,
      41,
      41,
      41,
      41,
      41,
      41,
      41,
      41,
      41,
      41,
      41,
      41,
      41,
      41,
      41,
      41,
      41,
      41,
      41,
      41,
      41,
      41,
      41,
      41,
      41,
      41,
      41,
      41,
      41,
      41
    ],
    "fp": [
      NaN,
      NaN,
      NaN,
      NaN,
      NaN,
      NaN,
      NaN,
      NaN,
      NaN,
      NaN,
      NaN,
      NaN,
      NaN,
      NaN,
      NaN,
      NaN,
      NaN,
      NaN,
      NaN,
      NaN,
      NaN,
      NaN,
      NaN,
      NaN,
      NaN,
      NaN,
      NaN,
      NaN,
      NaN,
      NaN,
      NaN,
      NaN,
      NaN,
      NaN,
      NaN,
      NaN,
      NaN,
      NaN,
      NaN,
      NaN
    ],
    "tp": [
      0.0,
      0.0,
      0.0,
      0.0,
      0.0,
      0.0,
      0.0,
      0.0,
      0.0,
      0.0,
      0.0,
      0.0,
      0.0,
      0.0,
      0.0,
      0.0,
      0.0,
      0.0,
      0.0,
      0.0,
      0.0,
      0.0,
      0.0,
      0.0,
      0.0,
      0.0,
      0.0,
      0.0,
      0.0,
      0.0,
      0.0,
      0.0,
      0.0,
      0.0,
      0.0,
      0.0,
      0.0,
      0.0,
      0.0,
      0.0
    ],
    "ids": [
      NaN,
      NaN,
      NaN,
      NaN,
      NaN,
      NaN,
      NaN,
      NaN,
      NaN,
      NaN,
      NaN,
      NaN,
      NaN,
      NaN,
      NaN,
      NaN,
      NaN,
      NaN,
      NaN,
      NaN,
      NaN,
      NaN,
      NaN,
      NaN,
      NaN,
      NaN,
      NaN,
      NaN,
      NaN,
      NaN,
      NaN,
      NaN,
      NaN,
      NaN,
      NaN,
      NaN,
      NaN,
      NaN,
      NaN,
      NaN
    ],
    "motar": [
      0.0,
      0.0,
      0.0,
      0.0,
      0.0,
      0.0,
      0.0,
      0.0,
      0.0,
      0.0,
      0.0,
      0.0,
      0.0,
      0.0,
      0.0,
      0.0,
      0.0,
      0.0,
      0.0,
      0.0,
      0.0,
      0.0,
      0.0,
      0.0,
      0.0,
      0.0,
      0.0,
      0.0,
      0.0,
      0.0,
      0.0,
      0.0,
      0.0,
      0.0,
      0.0,
      0.0,
      0.0,
      0.0,
      0.0,
      0.0
    ],
    "mt": [
      0.0,
      0.0,
      0.0,
      0.0,
      0.0,
      0.0,
      0.0,
      0.0,
      0.0,
      0.0,
      0.0,
      0.0,
      0.0,
      0.0,
      0.0,
      0.0,
      0.0,
      0.0,
      0.0,
      0.0,
      0.0,
      0.0,
      0.0,
      0.0,
      0.0,
      0.0,
      0.0,
      0.0,
      0.0,
      0.0,
      0.0,
      0.0,
      0.0,
      0.0,
      0.0,
      0.0,
      0.0,
      0.0,
      0.0,
      0.0
    ],
    "faf": [
      500,
      500,
      500,
      500,
      500,
      500,
      500,
      500,
      500,
      500,
      500,
      500,
      500,
      500,
      500,
      500,
      500,
      500,
      500,
      500,
      500,
      500,
      500,
      500,
      500,
      500,
      500,
      500,
      500,
      500,
      500,
      500,
      500,
      500,
      500,
      500,
      500,
      500,
      500,
      500
    ],
    "ml": [
      1,
      1,
      1,
      1,
      1,
      1,
      1,
      1,
      1,
      1,
      1,
      1,
      1,
      1,
      1,
      1,
      1,
      1,
      1,
      1,
      1,
      1,
      1,
      1,
      1,
      1,
      1,
      1,
      1,
      1,
      1,
      1,
      1,
      1,
      1,
      1,
      1,
      1,
      1,
      1
    ],
    "gt": [
      41,
      41,
      41,
      41,
      41,
      41,
      41,
      41,
      41,
      41,
      41,
      41,
      41,
      41,
      41,
      41,
      41,
      41,
      41,
      41,
      41,
      41,
      41,
      41,
      41,
      41,
      41,
      41,
      41,
      41,
      41,
      41,
      41,
      41,
      41,
      41,
      41,
      41,
      41,
      41
    ],
    "mota": [
      0.0,
      0.0,
      0.0,
      0.0,
      0.0,
      0.0,
      0.0,
      0.0,
      0.0,
      0.0,
      0.0,
      0.0,
      0.0,
      0.0,
      0.0,
      0.0,
      0.0,
      0.0,
      0.0,
      0.0,
      0.0,
      0.0,
      0.0,
      0.0,
      0.0,
      0.0,
      0.0,
      0.0,
      0.0,
      0.0,
      0.0,
      0.0,
      0.0,
      0.0,
      0.0,
      0.0,
      0.0,
      0.0,
      0.0,
      0.0
    ],
    "motp": [
      2.0,
      2.0,
      2.0,
      2.0,
      2.0,
      2.0,
      2.0,
      2.0,
      2.0,
      2.0,
      2.0,
      2.0,
      2.0,
      2.0,
      2.0,
      2.0,
      2.0,
      2.0,
      2.0,
      2.0,
      2.0,
      2.0,
      2.0,
      2.0,
      2.0,
      2.0,
      2.0,
      2.0,
      2.0,
      2.0,
      2.0,
      2.0,
      2.0,
      2.0,
      2.0,
      2.0,
      2.0,
      2.0,
      2.0,
      2.0
    ]
  },
  "truck": {
    "confidence": [
      NaN,
      NaN,
      NaN,
      NaN,
      NaN,
      NaN,
      NaN,
      NaN,
      NaN,
      NaN,
      NaN,
      NaN,
      NaN,
      NaN,
      NaN,
      NaN,
      NaN,
      NaN,
      NaN,
      NaN,
      NaN,
      NaN,
      NaN,
      NaN,
      NaN,
      0.49977967143058777,
      0.5719007074832916,
      0.5719007074832916,
      0.59046902,
      0.59046902,
      0.7615321956943427,
      0.7615321956943427,
      0.7615321956943427,
      0.7615321956943427,
      0.7615321956943427,
      0.7615321956943427,
      0.7654013690180387,
      0.8453642844486157,
      0.8453642844486157,
      0.8453642844486157
    ],
    "recall_hypo": [
      1.0,
      0.976923076923,
      0.953846153846,
      0.930769230769,
      0.907692307692,
      0.884615384615,
      0.861538461538,
      0.838461538462,
      0.815384615385,
      0.792307692308,
      0.769230769231,
      0.746153846154,
      0.723076923077,
      0.7,
      0.676923076923,
      0.653846153846,
      0.630769230769,
      0.607692307692,
      0.584615384615,
      0.561538461538,
      0.538461538462,
      0.515384615385,
      0.492307692308,
      0.469230769231,
      0.446153846154,
      0.423076923077,
      0.4,
      0.376923076923,
      0.353846153846,
      0.330769230769,
      0.307692307692,
      0.284615384615,
      0.261538461538,
      0.238461538462,
      0.215384615385,
      0.192307692308,
      0.169230769231,
      0.146153846154,
      0.123076923077,
      0.1
    ],
    "lgd": [
      NaN,
      NaN,
      NaN,
      NaN,
      NaN,
      NaN,
      NaN,
      NaN,
      NaN,
      NaN,
      NaN,
      NaN,
      NaN,
      NaN,
      NaN,
      NaN,
      NaN,
      NaN,
      NaN,
      NaN,
      NaN,
      NaN,
      NaN,
      NaN,
      NaN,
      2.9166666666666665,
      3.2,
      3.2,
      4.3,
      4.3,
      3.75,
      3.75,
      3.75,
      3.75,
      3.75,
      3.75,
      4.0,
      4.0,
      4.0,
      4.0
    ],
    "frag": [
      NaN,
      NaN,
      NaN,
      NaN,
      NaN,
      NaN,
      NaN,
      NaN,
      NaN,
      NaN,
      NaN,
      NaN,
      NaN,
      NaN,
      NaN,
      NaN,
      NaN,
      NaN,
      NaN,
      NaN,
      NaN,
      NaN,
      NaN,
      NaN,
      NaN,
      2.0,
      1.0,
      1.0,
      0.0,
      0.0,
      0.0,
      0.0,
      0.0,
      0.0,
      0.0,
      0.0,
      0.0,
      0.0,
      0.0,
      0.0
    ],
    "recall": [
      NaN,
      NaN,
      NaN,
      NaN,
      NaN,
      NaN,
      NaN,
      NaN,
      NaN,
      NaN,
      NaN,
      NaN,
      NaN,
      NaN,
      NaN,
      NaN,
      NaN,
      NaN,
      NaN,
      NaN,
      NaN,
      NaN,
      NaN,
      NaN,
      NaN,
      0.4576271186440678,
      0.4350282485875706,
      0.4350282485875706,
      0.3785310734463277,
      0.3785310734463277,
      0.3163841807909605,
      0.3163841807909605,
      0.3163841807909605,
      0.3163841807909605,
      0.3163841807909605,
      0.3163841807909605,
      0.1638418079096045,
      0.1638418079096045,
      0.1638418079096045,
      0.1638418079096045
    ],
    "tid": [
      NaN,
      NaN,
      NaN,
      NaN,
      NaN,
      NaN,
      NaN,
      NaN,
      NaN,
      NaN,
      NaN,
      NaN,
      NaN,
      NaN,
      NaN,
      NaN,
      NaN,
      NaN,
      NaN,
      NaN,
      NaN,
      NaN,
      NaN,
      NaN,
      NaN,
      1.9166666666666667,
      1.7,
      1.7,
      2.8,
      2.8,
      1.75,
      1.75,
      1.75,
      1.75,
      1.75,
      1.75,
      0.0,
      0.0,
      0.0,
      0.0
    ],
    "fn": [
      NaN,
      NaN,
      NaN,
      NaN,
      NaN,
      NaN,
      NaN,
      NaN,
      NaN,
      NaN,
      NaN,
      NaN,
      NaN,
      NaN,
      NaN,
      NaN,
      NaN,
      NaN,
      NaN,
      NaN,
      NaN,
      NaN,
      NaN,
      NaN,
      NaN,
      96.0,
      100.0,
      100.0,
      110.0,
      110.0,
      121.0,
      121.0,
      121.0,
      121.0,
      121.0,
      121.0,
      148.0,
      148.0,
      148.0,
      148.0
    ],
    "fp": [
      NaN,
      NaN,
      NaN,
      NaN,
      NaN,
      NaN,
      NaN,
      NaN,
      NaN,
      NaN,
      NaN,
      NaN,
      NaN,
      NaN,
      NaN,
      NaN,
      NaN,
      NaN,
      NaN,
      NaN,
      NaN,
      NaN,
      NaN,
      NaN,
      NaN,
      48.0,
      43.0,
      43.0,
      43.0,
      43.0,
      43.0,
      43.0,
      43.0,
      43.0,
      43.0,
      43.0,
      43.0,
      43.0,
      43.0,
      43.0
    ],
    "tp": [
      NaN,
      NaN,
      NaN,
      NaN,
      NaN,
      NaN,
      NaN,
      NaN,
      NaN,
      NaN,
      NaN,
      NaN,
      NaN,
      NaN,
      NaN,
      NaN,
      NaN,
      NaN,
      NaN,
      NaN,
      NaN,
      NaN,
      NaN,
      NaN,
      NaN,
      77.0,
      74.0,
      74.0,
      65.0,
      65.0,
      56.0,
      56.0,
      56.0,
      56.0,
      56.0,
      56.0,
      29.0,
      29.0,
      29.0,
      29.0
    ],
    "ids": [
      NaN,
      NaN,
      NaN,
      NaN,
      NaN,
      NaN,
      NaN,
      NaN,
      NaN,
      NaN,
      NaN,
      NaN,
      NaN,
      NaN,
      NaN,
      NaN,
      NaN,
      NaN,
      NaN,
      NaN,
      NaN,
      NaN,
      NaN,
      NaN,
      NaN,
      4.0,
      3.0,
      3.0,
      2.0,
      2.0,
      0.0,
      0.0,
      0.0,
      0.0,
      0.0,
      0.0,
      0.0,
      0.0,
      0.0,
      0.0
    ],
    "motar": [
      NaN,
      NaN,
      NaN,
      NaN,
      NaN,
      NaN,
      NaN,
      NaN,
      NaN,
      NaN,
      NaN,
      NaN,
      NaN,
      NaN,
      NaN,
      NaN,
      NaN,
      NaN,
      NaN,
      NaN,
      NaN,
      NaN,
      NaN,
      NaN,
      NaN,
      0.37662337662337664,
      0.4189189189189191,
      0.4189189189189191,
      0.33846153846153826,
      0.33846153846153826,
      0.2321428571428572,
      0.2321428571428572,
      0.2321428571428572,
      0.2321428571428572,
      0.2321428571428572,
      0.2321428571428572,
      0.0,
      0.0,
      0.0,
      0.0
    ],
    "mt": [
      NaN,
      NaN,
      NaN,
      NaN,
      NaN,
      NaN,
      NaN,
      NaN,
      NaN,
      NaN,
      NaN,
      NaN,
      NaN,
      NaN,
      NaN,
      NaN,
      NaN,
      NaN,
      NaN,
      NaN,
      NaN,
      NaN,
      NaN,
      NaN,
      NaN,
      0.0,
      0.0,
      0.0,
      0.0,
      0.0,
      0.0,
      0.0,
      0.0,
      0.0,
      0.0,
      0.0,
      0.0,
      0.0,
      0.0,
      0.0
    ],
    "faf": [
      NaN,
      NaN,
      NaN,
      NaN,
      NaN,
      NaN,
      NaN,
      NaN,
      NaN,
      NaN,
      NaN,
      NaN,
      NaN,
      NaN,
      NaN,
      NaN,
      NaN,
      NaN,
      NaN,
      NaN,
      NaN,
      NaN,
      NaN,
      NaN,
      NaN,
      40.33613445378151,
      36.134453781512605,
      36.134453781512605,
      36.134453781512605,
      36.134453781512605,
      36.134453781512605,
      36.134453781512605,
      36.134453781512605,
      36.134453781512605,
      36.134453781512605,
      36.134453781512605,
      36.134453781512605,
      36.134453781512605,
      36.134453781512605,
      36.134453781512605
    ],
    "ml": [
      NaN,
      NaN,
      NaN,
      NaN,
      NaN,
      NaN,
      NaN,
      NaN,
      NaN,
      NaN,
      NaN,
      NaN,
      NaN,
      NaN,
      NaN,
      NaN,
      NaN,
      NaN,
      NaN,
      NaN,
      NaN,
      NaN,
      NaN,
      NaN,
      NaN,
      4.0,
      4.0,
      4.0,
      5.0,
      5.0,
      7.0,
      7.0,
      7.0,
      7.0,
      7.0,
      7.0,
      8.0,
      8.0,
      8.0,
      8.0
    ],
    "gt": [
      NaN,
      NaN,
      NaN,
      NaN,
      NaN,
      NaN,
      NaN,
      NaN,
      NaN,
      NaN,
      NaN,
      NaN,
      NaN,
      NaN,
      NaN,
      NaN,
      NaN,
      NaN,
      NaN,
      NaN,
      NaN,
      NaN,
      NaN,
      NaN,
      NaN,
      177.0,
      177.0,
      177.0,
      177.0,
      177.0,
      177.0,
      177.0,
      177.0,
      177.0,
      177.0,
      177.0,
      177.0,
      177.0,
      177.0,
      177.0
    ],
    "mota": [
      NaN,
      NaN,
      NaN,
      NaN,
      NaN,
      NaN,
      NaN,
      NaN,
      NaN,
      NaN,
      NaN,
      NaN,
      NaN,
      NaN,
      NaN,
      NaN,
      NaN,
      NaN,
      NaN,
      NaN,
      NaN,
      NaN,
      NaN,
      NaN,
      NaN,
      0.16384180790960456,
      0.17514124293785316,
      0.17514124293785316,
      0.12429378531073443,
      0.12429378531073443,
      0.07344632768361581,
      0.07344632768361581,
      0.07344632768361581,
      0.07344632768361581,
      0.07344632768361581,
      0.07344632768361581,
      0.0,
      0.0,
      0.0,
      0.0
    ],
    "motp": [
      NaN,
      NaN,
      NaN,
      NaN,
      NaN,
      NaN,
      NaN,
      NaN,
      NaN,
      NaN,
      NaN,
      NaN,
      NaN,
      NaN,
      NaN,
      NaN,
      NaN,
      NaN,
      NaN,
      NaN,
      NaN,
      NaN,
      NaN,
      NaN,
      NaN,
      0.4588065523182235,
      0.44324207626384016,
      0.44324207626384016,
      0.4583511077321376,
      0.4583511077321376,
      0.39334003330549716,
      0.39334003330549716,
      0.39334003330549716,
      0.39334003330549716,
      0.39334003330549716,
      0.39334003330549716,
      0.4779564821264366,
      0.4779564821264366,
      0.4779564821264366,
      0.4779564821264366
    ]
  }
}